{
  "mouse": {
    "name": "ねずみ",
    "type": "grunt",
    "model": "enemies/mouse.glb",
    "texture": "enemies/mouse.png",
    "description": "小さくて素早い、チュートリアル向けの弱い敵",
    "scale": [0.6, 0.6, 0.6],
    "hp": 30,
    "speed": 1.5,
    "experience": 1,
    "weakAttack": {
      "damage": 3,
      "range": 0.6,
      "cooldown": 2000,
      "castTime": 100
    },
    "strongAttack": {
      "damage": 6,
      "range": 0.8,
      "cooldown": 5000,
      "castTime": 300,
      "probability": 0.15
    }
  },
  "crow": {
    "name": "カラス",
    "type": "grunt",
    "model": "enemies/crow.glb",
    "texture": "enemies/crow.png",
    "description": "空中から攻撃する小鳥、チュートリアル向け",
    "scale": [0.8, 0.8, 0.8],
    "hp": 40,
    "speed": 2.0,
    "experience": 3,
    "weakAttack": {
      "damage": 4,
      "range": 1.2,
      "cooldown": 1800,
      "castTime": 200
    },
    "strongAttack": {
      "damage": 8,
      "range": 1.5,
      "cooldown": 4500,
      "castTime": 400,
      "probability": 0.2
    }
  },
  "weasel": {
    "name": "イタチ",
    "type": "grunt",
    "model": "enemies/weasel.glb",
    "texture": "enemies/weasel.png",
    "description": "俊敏だが攻撃力は控えめなチュートリアル敵",
    "scale": [0.9, 0.9, 0.9],
    "hp": 50,
    "speed": 2.5,
    "experience": 5,
    "weakAttack": {
      "damage": 5,
      "range": 1.0,
      "cooldown": 1500,
      "castTime": 150
    },
    "strongAttack": {
      "damage": 10,
      "range": 1.3,
      "cooldown": 4000,
      "castTime": 350,
      "probability": 0.25
    }
  },
  "dog": {
    "name": "犬",
    "type": "boss",
    "model": "enemies/dog.glb",
    "texture": "enemies/dog.png",
    "description": "始まりの地のボス、チュートリアル最終試練",
    "scale": [1.2, 1.2, 1.2],
    "hp": 120,
    "speed": 1.8,
    "experience": 20,
    "weakAttack": {
      "damage": 12,
      "range": 1.8,
      "cooldown": 2000,
      "castTime": 250
    },
    "strongAttack": {
      "damage": 25,
      "range": 2.4,
      "cooldown": 5000,
      "castTime": 500,
      "probability": 0.4
    },
    "skills": {
      "packHowl": {
        "cooldown": 12000,
        "probability": 0.25
      },
      "boneBite": {
        "cooldown": 6000,
        "probability": 0.35
      },
      "barkBlast": {
        "cooldown": 8000,
        "probability": 0.3
      }
    }
  },
  "wolf": {
    "name": "オオカミ",
    "type": "grunt",
    "model": "enemies/wolf.glb",
    "texture": "enemies/wolf.png",
    "description": "呪われた森に潜む獰猛な狼、群れで行動する",
    "scale": [1.1, 1.1, 1.1],
    "hp": 80,
    "speed": 2.2,
    "experience": 4,
    "weakAttack": {
      "damage": 8,
      "range": 1.3,
      "cooldown": 1800,
      "castTime": 200
    },
    "strongAttack": {
      "damage": 16,
      "range": 1.6,
      "cooldown": 4000,
      "castTime": 400,
      "probability": 0.3
    }
  },
  "poisonMushroom": {
    "name": "毒キノコ",
    "type": "grunt",
    "model": "enemies/poison-mushroom.glb",
    "texture": "enemies/poison-mushroom.png",
    "description": "森の奥に隠れる毒々しいキノコ、毒胞子を放つ",
    "scale": [0.7, 0.7, 0.7],
    "hp": 60,
    "speed": 0.8,
    "experience": 3,
    "weakAttack": {
      "damage": 5,
      "range": 1.0,
      "cooldown": 2500,
      "castTime": 300
    },
    "strongAttack": {
      "damage": 10,
      "range": 1.5,
      "cooldown": 5000,
      "castTime": 500,
      "probability": 0.25
    },
    "skills": {
      "poisonSpray": {
        "cooldown": 6000,
        "probability": 0.4
      }
    }
  },
  "treeGuardian": {
    "name": "森の守護樹",
    "type": "boss",
    "model": "enemies/tree-guardian.glb",
    "texture": "enemies/tree-guardian.png",
    "description": "呪われた森の古い守護者、毒と束縛の力を持つ",
    "scale": [2.0, 2.0, 2.0],
    "hp": 200,
    "speed": 0.5,
    "experience": 30,
    "weakAttack": {
      "damage": 15,
      "range": 4.0,
      "cooldown": 3000,
      "castTime": 400
    },
    "strongAttack": {
      "damage": 30,
      "range": 5.0,
      "cooldown": 6000,
      "castTime": 600,
      "probability": 0.3
    },
    "skills": {
      "poisonSpores": {
        "cooldown": 10000,
        "probability": 0.3
      },
      "rootBind": {
        "cooldown": 8000,
        "probability": 0.35
      },
      "barkShield": {
        "cooldown": 15000,
        "probability": 0.2
      }
    }
  },
  "gargoyle": {
    "name": "ガーゴイル",
    "type": "grunt",
    "model": "enemies/gargoyle.glb",
    "texture": "enemies/gargoyle.png",
    "description": "古城の守護石像。石の体を持ち、高い防御力を誇る",
    "scale": [1.3, 1.3, 1.3],
    "hp": 120,
    "speed": 1.0,
    "experience": 8,
    "weakAttack": {
      "damage": 12,
      "range": 1.5,
      "cooldown": 2200,
      "castTime": 300
    },
    "strongAttack": {
      "damage": 24,
      "range": 2.0,
      "cooldown": 5000,
      "castTime": 500,
      "probability": 0.3
    },
    "skills": {
      "stoneShield": {
        "cooldown": 8000,
        "probability": 0.4
      }
    }
  },
  "ghost": {
    "name": "亡霊",
    "type": "grunt",
    "model": "enemies/ghost.glb",
    "texture": "enemies/ghost.png",
    "description": "古城に縛られた魂。物理攻撃への耐性を持つ",
    "scale": [1.0, 1.0, 1.0],
    "hp": 90,
    "speed": 1.8,
    "experience": 6,
    "weakAttack": {
      "damage": 10,
      "range": 1.2,
      "cooldown": 1800,
      "castTime": 200
    },
    "strongAttack": {
      "damage": 20,
      "range": 1.8,
      "cooldown": 4200,
      "castTime": 400,
      "probability": 0.35
    },
    "skills": {
      "phaseShift": {
        "cooldown": 6000,
        "probability": 0.3
      }
    }
  },
  "ancientGuardian": {
    "name": "古代の守護者",
    "type": "boss",
    "model": "enemies/ancient-guardian.glb",
    "texture": "enemies/ancient-guardian.png",
    "description": "古城の最深部を守る古き守護者。強力な魔法攻撃を使う",
    "scale": [1.8, 1.8, 1.8],
    "hp": 280,
    "speed": 0.8,
    "experience": 40,
    "weakAttack": {
      "damage": 18,
      "range": 2.2,
      "cooldown": 2800,
      "castTime": 400
    },
    "strongAttack": {
      "damage": 35,
      "range": 3.0,
      "cooldown": 6500,
      "castTime": 700,
      "probability": 0.4
    },
    "skills": {
      "ancientMagic": {
        "cooldown": 12000,
        "probability": 0.35
      },
      "guardianBarrier": {
        "cooldown": 18000,
        "probability": 0.25
      }
    }
  },
  "iceGolem": {
    "name": "アイスゴーレム",
    "type": "grunt",
    "model": "enemies/ice-golem.glb",
    "texture": "enemies/ice-golem.png",
    "description": "氷の魔力で作り出された巨大な人形。氷属性攻撃を使う",
    "scale": [1.5, 1.5, 1.5],
    "hp": 150,
    "speed": 0.6,
    "experience": 10,
    "weakAttack": {
      "damage": 15,
      "range": 1.8,
      "cooldown": 3000,
      "castTime": 400
    },
    "strongAttack": {
      "damage": 30,
      "range": 2.5,
      "cooldown": 6000,
      "castTime": 600,
      "probability": 0.3
    },
    "skills": {
      "iceSpike": {
        "cooldown": 7000,
        "probability": 0.4
      }
    }
  },
  "snowWolf": {
    "name": "雪狼",
    "type": "grunt",
    "model": "enemies/snow-wolf.glb",
    "texture": "enemies/snow-wolf.png",
    "description": "雪山に住む白い毛皮の狼。群れで協調攻撃を仕掛ける",
    "scale": [1.1, 1.1, 1.1],
    "hp": 100,
    "speed": 2.5,
    "experience": 7,
    "weakAttack": {
      "damage": 12,
      "range": 1.4,
      "cooldown": 1600,
      "castTime": 180
    },
    "strongAttack": {
      "damage": 24,
      "range": 1.8,
      "cooldown": 3800,
      "castTime": 350,
      "probability": 0.35
    },
    "skills": {
      "packHunt": {
        "cooldown": 8000,
        "probability": 0.4
      }
    }
  },
  "iceSpirit": {
    "name": "氷の精霊",
    "type": "grunt",
    "model": "enemies/ice-spirit.glb",
    "texture": "enemies/ice-spirit.png",
    "description": "雪山の寒さが生み出した氷の精霊。氷の魔法を操る",
    "scale": [0.8, 0.8, 0.8],
    "hp": 80,
    "speed": 2.0,
    "experience": 9,
    "weakAttack": {
      "damage": 8,
      "range": 2.0,
      "cooldown": 2000,
      "castTime": 250
    },
    "strongAttack": {
      "damage": 16,
      "range": 2.5,
      "cooldown": 4500,
      "castTime": 450,
      "probability": 0.4
    },
    "skills": {
      "frostBolt": {
        "cooldown": 5000,
        "probability": 0.5
      }
    }
  },
  "frostDragon": {
    "name": "フロストドラゴン",
    "type": "boss",
    "model": "enemies/frost-dragon.glb",
    "texture": "enemies/frost-dragon.png",
    "description": "雪山の頂きに住む氷の竜。強力な氷のブレスを吐く",
    "scale": [2.5, 2.5, 2.5],
    "hp": 350,
    "speed": 1.5,
    "experience": 50,
    "weakAttack": {
      "damage": 22,
      "range": 6.25,
      "cooldown": 2500,
      "castTime": 350
    },
    "strongAttack": {
      "damage": 45,
      "range": 10.0,
      "cooldown": 7000,
      "castTime": 800,
      "probability": 0.4
    },
    "skills": {
      "iceBreath": {
        "cooldown": 10000,
        "probability": 0.4
      },
      "blizzardCall": {
        "cooldown": 15000,
        "probability": 0.3
      }
    }
  },
  "lavaSlime": {
    "name": "溶岩スライム",
    "type": "grunt",
    "model": "enemies/lava-slime.glb",
    "texture": "enemies/lava-slime.png",
    "description": "溶岩の中で生まれたスライム。炎属性攻撃と分裂能力を持つ",
    "scale": [0.9, 0.9, 0.9],
    "hp": 60,
    "speed": 1.2,
    "experience": 5,
    "weakAttack": {
      "damage": 8,
      "range": 1.0,
      "cooldown": 1500,
      "castTime": 150
    },
    "strongAttack": {
      "damage": 16,
      "range": 1.5,
      "cooldown": 3500,
      "castTime": 300,
      "probability": 0.3
    },
    "skills": {
      "lavaSplash": {
        "cooldown": 4000,
        "probability": 0.4
      }
    }
  },
  "rockElemental": {
    "name": "岩石エレメンタル",
    "type": "grunt",
    "model": "enemies/rock-elemental.glb",
    "texture": "enemies/rock-elemental.png",
    "description": "洞窟の岩石に宿った精霊。高い防御力と地震攻撃を持つ",
    "scale": [1.4, 1.4, 1.4],
    "hp": 180,
    "speed": 0.8,
    "experience": 12,
    "weakAttack": {
      "damage": 18,
      "range": 1.6,
      "cooldown": 2800,
      "castTime": 400
    },
    "strongAttack": {
      "damage": 36,
      "range": 2.2,
      "cooldown": 6000,
      "castTime": 600,
      "probability": 0.35
    },
    "skills": {
      "rockThrow": {
        "cooldown": 6000,
        "probability": 0.4
      }
    }
  },
  "shadowWraith": {
    "name": "影の亡霊",
    "type": "grunt",
    "model": "enemies/shadow-wraith.glb",
    "texture": "enemies/shadow-wraith.png",
    "description": "深淵の闇から現れた影の化身。暗黒魔法を使う",
    "scale": [1.2, 1.2, 1.2],
    "hp": 110,
    "speed": 2.2,
    "experience": 14,
    "weakAttack": {
      "damage": 14,
      "range": 1.8,
      "cooldown": 2000,
      "castTime": 250
    },
    "strongAttack": {
      "damage": 28,
      "range": 2.2,
      "cooldown": 4800,
      "castTime": 500,
      "probability": 0.4
    },
    "skills": {
      "shadowBind": {
        "cooldown": 7000,
        "probability": 0.35
      }
    }
  },
  "abyssDragon": {
    "name": "深淵ドラゴン",
    "type": "boss",
    "model": "enemies/abyss-dragon.glb",
    "texture": "enemies/abyss-dragon.png",
    "description": "深淵の洞窟の奥深くに住む古代の竜。猫又に仕える強力な守護者",
    "scale": [3.0, 3.0, 3.0],
    "hp": 400,
    "speed": 1.0,
    "experience": 60,
    "weakAttack": {
      "damage": 20,
      "range": 7.5,
      "cooldown": 2800,
      "castTime": 400
    },
    "strongAttack": {
      "damage": 40,
      "range": 10.5,
      "cooldown": 6500,
      "castTime": 900,
      "probability": 0.4
    },
    "skills": {
      "dragonBreath": {
        "cooldown": 12000,
        "probability": 0.4,
        "description": "炎のブレスで前方広範囲を焼き尽くす"
      },
      "wingStorm": {
        "cooldown": 15000,
        "probability": 0.3,
        "description": "翼で突風を起こし、敵を吹き飛ばす"
      },
      "dragonRoar": {
        "cooldown": 18000,
        "probability": 0.25,
        "description": "咆哮で周囲の敵を恐怖状態にする"
      }
    }
  },
  "nekomata": {
    "name": "猫又",
    "type": "boss",
    "model": "enemies/nekomata.glb",
    "texture": "enemies/nekomata.png",
    "description": "呪いの根源であり、王国の滅亡を引き起こした存在。ラスボス。",
    "scale": [1.6, 1.6, 1.6],
    "hp": 500,
    "speed": 1.2,
    "experience": 100,
    "weakAttack": {
      "damage": 25,
      "range": 3.2,
      "cooldown": 2500,
      "castTime": 300
    },
    "strongAttack": {
      "damage": 50,
      "range": 4.8,
      "cooldown": 6000,
      "castTime": 800,
      "probability": 0.35
    },
    "skills": {
      "curseBlast": {
        "cooldown": 15000,
        "probability": 0.3,
        "description": "呪いの力を放ち、広範囲にダメージを与える"
      },
      "shadowClone": {
        "cooldown": 20000,
        "probability": 0.25,
        "description": "影分身を作り出し、複数方向から攻撃する"
      },
      "nineTails": {
        "cooldown": 25000,
        "probability": 0.2,
        "description": "九本の尻尾で連続攻撃を繰り出す最強スキル"
      }
    }
  }
}
